LICENSE
README.md
setup.py
pypsxlib/__init__.py
pypsxlib/utils.py
pypsxlib.egg-info/PKG-INFO
pypsxlib.egg-info/SOURCES.txt
pypsxlib.egg-info/dependency_links.txt
pypsxlib.egg-info/requires.txt
pypsxlib.egg-info/top_level.txt