Metadata-Version: 2.1
Name: pypsxlib
Version: 0.2.0
Summary: Library for reading, modifying and writing Agisoft Photoscan/Metashape PSX projects.
Home-page: https://gitlab.com/dodgyville/pypsxlib
Author: Luke Miller
Author-email: dodgyville@gmail.com
License: UNKNOWN
Platform: UNKNOWN
Classifier: Programming Language :: Python :: 3
Classifier: License :: OSI Approved :: MIT License
Classifier: Operating System :: OS Independent
Requires-Python: >=3.6
License-File: LICENSE
